DataPrepKitV2/__init__.py
DataPrepKitV2/categorical_encoding.py
DataPrepKitV2/data_reader.py
DataPrepKitV2/data_summary.py
DataPrepKitV2/missing_values.py
DataPrepKitV2/test_categorical_encoding.py
DataPrepKitV2/test_data_reader.py
DataPrepKitV2/test_data_summary.py
DataPrepKitV2/test_missing_values.py
DataPrepKitV2-2.0.dist-info/METADATA
DataPrepKitV2-2.0.dist-info/WHEEL
DataPrepKitV2-2.0.dist-info/top_level.txt
DataPrepKitV2-2.0.dist-info/RECORD
